{"walletName": "examplewallet1", "walletKey": "examplewallet1", "walletPath": null, "verityUrl": "https://vas.pps.evernym.com", "verityPublicDID": "Sc1rzepMCAXWXMjK6yj6iR", "verityPublicVerKey": "ExPFLx4uNjF9jRQJV7XxAt8MfuXJENgbgA1qNmWznsRZ", "domainDID": "XMAkUK22mrpcp8h5jPFhnW", "verityAgentVerKey": "2xnDXq14Y7MYA3KUxJY591ZkzRyZb6YHEsdtEG1xTthn", "sdkVerKeyId": "GX3yxHcSEUcqeNKEpGsR4A", "sdkVerKey": "9TZQAxoPNHcqgGPuU353UySKZwVkpoaNuKb2mw2QcCU4", "endpointUrl": "http://0055c7b01f8a.ngrok.io", "version": "0.2"}